<creature name="Elfo_ABJ__" level="260" merchant="0" clan="1" class="1" experience="97000" gold="9999" >
	<health now="30000" max="30000" regen="0" />
	<status str="6" dex="90" int="75" con="0" />
	<special special1="255" special2="1" special3="255" special4="24" />
	<strategy damage="400" magic="0" critical="255" attack_speed="243" move_speed="15" defense="1500"/>
	<look>
		<corpse id="287" brightness="9" />
		<helmet id="287" brightness="9" />
		<armor id="289" brightness="9" />
		<pants id="287" brightness="9" />
		<glove id="287" brightness="9" />
		<boots id="287" brightness="9" />
		<rigth_weapon id="741" brightness="8" />
		<left_weapon id="742" brightness="9" />
		<kingdom id="738" brightness="0" />
	</look>
</creature>