<summon name="Succubus" id="7" level="4" merchant="0" clan="4" class="1" experience="0" gold="0" >
	<health now="7500" max="7500" regen="0" />
	<status str="100" dex="500" int="500" con="1600" />
	<special special1="255" special2="6" special3="108" special4="5" />
	<strategy damage="60" magic="0" critical="255" attack_speed="0" move_speed="5" defense="30"/>
	<resistences>
		<resistence holy="40" />
		<resistence lightning="40" />
		<resistence fire="40" />
		<resistence ice="40" />
	</resistences>
	<look>
		<corpse id="396" brightness="0" />
		<guild id="508" brightness="0" />
		<eventitem id="786" brightness="0" />
	</look>
</summon>